<?xml version="1.0" encoding="UTF-8"?>
<objects serializationModel="Studio.02.03.00">
	<object class="AudioFile" id="{7a142dcc-1972-402c-a278-ea8c5c8b5633}">
		<property name="assetPath">
			<value>Maevis/Die_Maevis.wav</value>
		</property>
		<property name="frequencyInKHz">
			<value>44.0999985</value>
		</property>
		<property name="channelCount">
			<value>1</value>
		</property>
		<property name="length">
			<value>0.40344671201814059</value>
		</property>
		<relationship name="masterAssetFolder">
			<destination>{de0db2f1-8f41-4c02-a479-687435027c9f}</destination>
		</relationship>
	</object>
</objects>
