<?xml version="1.0" encoding="UTF-8"?>
<objects serializationModel="Studio.02.03.00">
	<object class="AudioFile" id="{e33d9212-44e0-4404-8b79-d4ce9d884224}">
		<property name="assetPath">
			<value>Maevis/SomDePulo_DreadFall.wav</value>
		</property>
		<property name="frequencyInKHz">
			<value>44.0999985</value>
		</property>
		<property name="channelCount">
			<value>1</value>
		</property>
		<property name="length">
			<value>0.58848072562358278</value>
		</property>
		<relationship name="masterAssetFolder">
			<destination>{de0db2f1-8f41-4c02-a479-687435027c9f}</destination>
		</relationship>
	</object>
</objects>
